[{"data":{"id":"Upload-Coverage-Report","source":null,"target":null}},{"data":{"id":"cfface5e-ef81-402a-b0bd-03e801ff179d","source":"Upload-Coverage-Report","target":"Upload-Coveralls-Report"}},{"data":{"id":"3b2fa0c8-ac0e-4c20-a18c-198b7e5e6754","source":"Upload-Coverage-Report","target":"Upload-Codecov-Report"}},{"data":{"id":"Upload-Codecov-Report","source":null,"target":null}},{"data":{"id":"7af4cb20-ee40-4024-8085-ca7d196fb4e4","source":"Upload-Codecov-Report","target":"Test"}},{"data":{"id":"Test","source":null,"target":null}},{"data":{"id":"99335ce5-0d1f-4ce1-8eb2-fd778aae8162","source":"Test","target":"DotNetCore-Build"}},{"data":{"id":"1e6788b0-4e5c-46f2-a1bd-9a7d209c4019","source":"Test","target":"DotNetCore-Test"}},{"data":{"id":"DotNetCore-Test","source":null,"target":null}},{"data":{"id":"e82350a5-6199-4a6d-ab43-2e51a483c24c","source":"DotNetCore-Test","target":"Install-OpenCover"}},{"data":{"id":"Install-OpenCover","source":null,"target":null}},{"data":{"id":"b183bdce-08a2-4065-b890-c3a66ffa1fe5","source":"Install-OpenCover","target":"Install-ReportGenerator"}},{"data":{"id":"Install-ReportGenerator","source":null,"target":null}},{"data":{"id":"1a754656-e946-4676-9097-1a47e6507431","source":"Install-ReportGenerator","target":"DotNetCore-Build"}},{"data":{"id":"DotNetCore-Build","source":null,"target":null}},{"data":{"id":"cabd94d2-e673-4e2f-9b5d-312e23a71728","source":"DotNetCore-Build","target":"Clean"}},{"data":{"id":"91dad5b9-1780-4317-8e93-c472b2edb600","source":"DotNetCore-Build","target":"DotNetCore-Restore"}},{"data":{"id":"DotNetCore-Restore","source":null,"target":null}},{"data":{"id":"Clean","source":null,"target":null}},{"data":{"id":"8590a975-36ce-44fe-aa76-bfabaa7bb405","source":"Clean","target":"Show-Info"}},{"data":{"id":"6cd1031b-46a1-4d7f-b880-13df424b0edd","source":"Clean","target":"Print-AppVeyor-Environment-Variables"}},{"data":{"id":"Print-AppVeyor-Environment-Variables","source":null,"target":null}},{"data":{"id":"Show-Info","source":null,"target":null}},{"data":{"id":"DotNetCore-Build","source":null,"target":null}},{"data":{"id":"a2c02467-6ba0-467b-bdb3-3b20757d9781","source":"DotNetCore-Build","target":"Clean"}},{"data":{"id":"425852d1-fe7b-4557-9cc0-8356fb87e39c","source":"DotNetCore-Build","target":"DotNetCore-Restore"}},{"data":{"id":"DotNetCore-Restore","source":null,"target":null}},{"data":{"id":"Clean","source":null,"target":null}},{"data":{"id":"ffe8b5bf-115f-4bb4-9518-aab89d9a64a3","source":"Clean","target":"Show-Info"}},{"data":{"id":"6e31bdb1-965a-4422-8885-6ff137236769","source":"Clean","target":"Print-AppVeyor-Environment-Variables"}},{"data":{"id":"Print-AppVeyor-Environment-Variables","source":null,"target":null}},{"data":{"id":"Show-Info","source":null,"target":null}},{"data":{"id":"Upload-Coveralls-Report","source":null,"target":null}},{"data":{"id":"7f074393-304c-4339-9103-1018091961f9","source":"Upload-Coveralls-Report","target":"Test"}},{"data":{"id":"Test","source":null,"target":null}},{"data":{"id":"6c882796-bb75-4ab2-864d-1eb9b57e55cd","source":"Test","target":"DotNetCore-Build"}},{"data":{"id":"125aa1d7-0393-4d9b-8852-718a9e945f10","source":"Test","target":"DotNetCore-Test"}},{"data":{"id":"DotNetCore-Test","source":null,"target":null}},{"data":{"id":"13ea73e8-d670-4f97-92ad-93ddd04bed8a","source":"DotNetCore-Test","target":"Install-OpenCover"}},{"data":{"id":"Install-OpenCover","source":null,"target":null}},{"data":{"id":"8b29c4cf-e91c-408c-9d67-b4d522167d11","source":"Install-OpenCover","target":"Install-ReportGenerator"}},{"data":{"id":"Install-ReportGenerator","source":null,"target":null}},{"data":{"id":"db16bcbc-c5f4-4507-ae37-35a383f58cd0","source":"Install-ReportGenerator","target":"DotNetCore-Build"}},{"data":{"id":"DotNetCore-Build","source":null,"target":null}},{"data":{"id":"1516a84f-3737-49b8-a1b5-93ede64d46f5","source":"DotNetCore-Build","target":"Clean"}},{"data":{"id":"0d4543db-9a5f-4713-ac21-b6d4f829a87b","source":"DotNetCore-Build","target":"DotNetCore-Restore"}},{"data":{"id":"DotNetCore-Restore","source":null,"target":null}},{"data":{"id":"Clean","source":null,"target":null}},{"data":{"id":"f8c00d62-3fca-4070-9237-8c6557f68c6b","source":"Clean","target":"Show-Info"}},{"data":{"id":"777be7db-5e2d-4883-9ab9-42e22ff0e370","source":"Clean","target":"Print-AppVeyor-Environment-Variables"}},{"data":{"id":"Print-AppVeyor-Environment-Variables","source":null,"target":null}},{"data":{"id":"Show-Info","source":null,"target":null}},{"data":{"id":"DotNetCore-Build","source":null,"target":null}},{"data":{"id":"0036bbaf-4283-4d48-a519-178317c52400","source":"DotNetCore-Build","target":"Clean"}},{"data":{"id":"575e2382-f49d-4913-9a8e-724cf47b73f8","source":"DotNetCore-Build","target":"DotNetCore-Restore"}},{"data":{"id":"DotNetCore-Restore","source":null,"target":null}},{"data":{"id":"Clean","source":null,"target":null}},{"data":{"id":"e85cab27-69a0-45af-9ce6-fbf5e5253844","source":"Clean","target":"Show-Info"}},{"data":{"id":"9c388555-537a-4d3d-b90b-af8932b8d52b","source":"Clean","target":"Print-AppVeyor-Environment-Variables"}},{"data":{"id":"Print-AppVeyor-Environment-Variables","source":null,"target":null}},{"data":{"id":"Show-Info","source":null,"target":null}}]